dbcc/__init__.py
dbcc/base.py
dbcc/mongodb.py
dbcc/tests/__init__.py
dbcc/tests/mongodb.py
dbcc-0.1.1.dist-info/AUTHORS
dbcc-0.1.1.dist-info/LICENSE
dbcc-0.1.1.dist-info/METADATA
dbcc-0.1.1.dist-info/WHEEL
dbcc-0.1.1.dist-info/top_level.txt
dbcc-0.1.1.dist-info/RECORD
